test/__init__.py
test/test_wikiapi.py
test/test_wikimultisearch.py
test/test_wikisearch.py
test/test_wikitext.py
test/timings.py
wikigeo/__init__.py
wikigeo/wikimultisearch.py
wikigeo/wikisearch.py
wikigeo/wikisource/__init__.py
wikigeo/wikisource/wikiapi.py
wikigeo/wikisource/wikitext.py
wikigeo-1.3.0.dist-info/LICENSE
wikigeo-1.3.0.dist-info/METADATA
wikigeo-1.3.0.dist-info/WHEEL
wikigeo-1.3.0.dist-info/top_level.txt
wikigeo-1.3.0.dist-info/RECORD
