Metadata-Version: 2.1
Name: wikigeo
Version: 1.3.0
Summary: Getting point of interest data by geographic coordinates from Wikipedia
Home-page: https://github.com/mmc1718/wikigeo
Author: Mary McGuire
Author-email: marymcguire1718@gmail.com
License: UNKNOWN
Platform: UNKNOWN
Classifier: Programming Language :: Python :: 3.8
Classifier: Programming Language :: Python :: 3.7
Classifier: Operating System :: OS Independent
Classifier: License :: OSI Approved :: MIT License
Classifier: Topic :: Internet :: WWW/HTTP :: Dynamic Content :: Wiki
Requires-Dist: requests-html
Requires-Dist: googletrans
Requires-Dist: fuzzywuzzy
Requires-Dist: python-Levenshtein-wheels
Provides-Extra: pytest
Requires-Dist: pytest (==6.0.1) ; extra == 'pytest'
Provides-Extra: tox
Requires-Dist: tox (==3.19.0) ; extra == 'tox'
